numpycythonpermutations/README.MD
numpycythonpermutations/__init__.py
numpycythonpermutations/requirements.txt
numpycythonpermutations/thirdparty.json
numpycythonpermutations/uniqueproductcython.pyx
numpycythonpermutations/xxhash.c
numpycythonpermutations/xxhash.h
numpycythonpermutations-0.10.dist-info/LICENSE.rst
numpycythonpermutations-0.10.dist-info/METADATA
numpycythonpermutations-0.10.dist-info/WHEEL
numpycythonpermutations-0.10.dist-info/top_level.txt
numpycythonpermutations-0.10.dist-info/RECORD
