Metadata-Version: 2.1
Name: numpycythonpermutations
Version: 0.10
Summary: Permutations, Combinations and Product for Numpy - written in Cython - 20x faster than itertools
Home-page: https://github.com/hansalemaos/numpycythonpermutations
Author: Johannes Fischer
Author-email: aulasparticularesdealemaosp@gmail.com
License: MIT
Keywords: Permutations,numpy,Combinations,Product
Classifier: Development Status :: 4 - Beta
Classifier: Programming Language :: Python :: 3 :: Only
Classifier: Programming Language :: Python :: 3.10
Classifier: Topic :: Software Development :: Libraries :: Python Modules
Classifier: Topic :: Utilities
License-File: LICENSE.rst
Requires-Dist: cycompi
Requires-Dist: flatten-any-dict-iterable-or-whatsoever
Requires-Dist: numpy
